ez_setup.py
index.html
setup.py
tilecache.cfg
tilecache.cgi
tilecache.fcgi
tilecache_clean.py
tilecache_http_server.py
tilecache_install_config.py
tilecache_seed.py
TileCache/Cache.py
TileCache/Client.py
TileCache/Layer.py
TileCache/Service.py
TileCache/Swarm.py
TileCache/__init__.py
TileCache.egg-info/PKG-INFO
TileCache.egg-info/SOURCES.txt
TileCache.egg-info/dependency_links.txt
TileCache.egg-info/not-zip-safe
TileCache.egg-info/top_level.txt
TileCache/Caches/AWSS3.py
TileCache/Caches/Disk.py
TileCache/Caches/Memcached.py
TileCache/Caches/S3.py
TileCache/Caches/__init__.py
TileCache/Layers/ArcXML.py
TileCache/Layers/Image.py
TileCache/Layers/MapServer.py
TileCache/Layers/Mapnik.py
TileCache/Layers/WMS.py
TileCache/Layers/__init__.py
TileCache/Peer/Twisted.py
TileCache/Services/KML.py
TileCache/Services/MGMaps.py
TileCache/Services/TMS.py
TileCache/Services/TileService.py
TileCache/Services/WMS.py
TileCache/Services/WMTS.py
TileCache/Services/WorldWind.py
TileCache/Services/__init__.py
debian/README.Debian
debian/changelog
debian/compat
debian/control
debian/copyright
debian/dirs
debian/docs
debian/examples
debian/manpages
debian/rules
debian/tilecache.8
debian/tilecache.cfg.5
debian/tilecache_clean.8
debian/tilecache_http_server.8
debian/tilecache_seed.8
debian/watch
docs/CONTRIBUTORS.txt
docs/Caches.txt
docs/EXAMPLES.txt
docs/Example.py.txt
docs/LICENSE.txt
docs/NEWS.txt
docs/README.txt
tests/HACKING.swarm.txt
tests/HACKING.txt
tests/Service.txt
tests/__init__.py
tests/tests.py
