Metadata-Version: 1.0
Name: TileCache
Version: 2.01
Summary: a web map tile caching system
Home-page: http://tilecache.org/
Author: MetaCarta Labs
Author-email: tilecache@openlayers.org
License: BSD
Platform: UNKNOWN
Classifier: Development Status :: 4 - Beta
Classifier: Intended Audience :: Developers
Classifier: Intended Audience :: Science/Research
Classifier: License :: OSI Approved :: BSD License
Classifier: Operating System :: OS Independent
Classifier: Programming Language :: Python
Classifier: Topic :: Scientific/Engineering :: GIS
